studiosr/__init__.py
studiosr/__main__.py
studiosr/data/__init__.py
studiosr/data/dataset.py
studiosr/data/handler.py
studiosr/data/transforms.py
studiosr/engine/__init__.py
studiosr/engine/evaluator.py
studiosr/engine/trainer.py
studiosr/models/__init__.py
studiosr/models/common.py
studiosr/models/edsr.py
studiosr/models/espcn.py
studiosr/models/han.py
studiosr/models/hat.py
studiosr/models/imdn.py
studiosr/models/maxsr.py
studiosr/models/rcan.py
studiosr/models/srcnn.py
studiosr/models/srresnet.py
studiosr/models/swinfir.py
studiosr/models/swinir.py
studiosr/models/vdsr.py
studiosr/utils/__init__.py
studiosr/utils/compare.py
studiosr/utils/helpers.py
studiosr/utils/losses.py
studiosr/utils/metrics.py
studiosr-0.1.14.dist-info/LICENSE
studiosr-0.1.14.dist-info/METADATA
studiosr-0.1.14.dist-info/WHEEL
studiosr-0.1.14.dist-info/top_level.txt
studiosr-0.1.14.dist-info/RECORD
